{"v":5,"entries":{"sak-sak-dokumenter--default":{"type":"story","id":"sak-sak-dokumenter--default","name":"Default","title":"sak/sak-dokumenter","importPath":"./src/DokumenterSakIndex.stories.tsx","componentPath":"./src/DokumenterSakIndex.tsx","tags":["dev","test"]},"sak-sak-dokumenter--ingen-dokumenter":{"type":"story","id":"sak-sak-dokumenter--ingen-dokumenter","name":"Ingen Dokumenter","title":"sak/sak-dokumenter","importPath":"./src/DokumenterSakIndex.stories.tsx","componentPath":"./src/DokumenterSakIndex.tsx","tags":["dev","test"]}}}